line_plan_visualization/__init__.py
line_plan_visualization/default_appearance.py
line_plan_visualization/line_plan.py
line_plan_visualization/physical_railway.py
line_plan_visualization/train_lines.py
line_plan_visualization-0.0.6.dist-info/LICENSE
line_plan_visualization-0.0.6.dist-info/METADATA
line_plan_visualization-0.0.6.dist-info/WHEEL
line_plan_visualization-0.0.6.dist-info/top_level.txt
line_plan_visualization-0.0.6.dist-info/RECORD
