Metadata-Version: 2.1
Name: line-plan-visualization
Version: 0.0.6
Summary: A visualization tool for line plan
Home-page: https://github.com/SteppePrince/LinePlanVisualization
Author: Macroda
Author-email: SteppePrince@outlook.com
Requires-Python: >=3.9
License-File: LICENSE
Requires-Dist: matplotlib >=3.7.3
